{
  "workoutTypes": {
    "Warrior 2": {
      "name": "Warrior 2",
      "code": "",
      "sessions": [
        {
          "date": "2025-11-01",
          "totalCapacity": 14383.5,
          "durationMinute": 65,
          "calorie": 352,
          "actionNum": 34
        },
        {
          "date": "2025-12-12",
          "totalCapacity": 9018.0,
          "durationMinute": 65,
          "calorie": 436,
          "actionNum": 34
        },
        {
          "date": "2025-12-15",
          "totalCapacity": 41058.0,
          "durationMinute": 65,
          "calorie": 1511,
          "actionNum": 34
        },
        {
          "date": "2026-01-07",
          "totalCapacity": 20698.0,
          "durationMinute": 66,
          "calorie": 1011,
          "actionNum": 34
        },
        {
          "date": "2026-01-11",
          "totalCapacity": 41481.5,
          "durationMinute": 66,
          "calorie": 1371,
          "actionNum": 34
        },
        {
          "date": "2026-01-27",
          "totalCapacity": 22014.5,
          "durationMinute": 64,
          "calorie": 939,
          "actionNum": 34
        },
        {
          "date": "2026-02-12",
          "totalCapacity": 21623.0,
          "durationMinute": 64,
          "calorie": 889,
          "actionNum": 34
        }
      ],
      "exercises": [],
      "muscles": [],
      "bestSession": {
        "date": "2026-01-11",
        "totalCapacity": 41481.5,
        "durationMinute": 66,
        "calorie": 1371,
        "actionNum": 34
      },
      "totalSessions": 7,
      "avgVolume": 24325.2,
      "totalVolume": 170276.5
    },
    "Arms Barbell": {
      "name": "Arms Barbell",
      "code": "",
      "sessions": [
        {
          "date": "2025-11-01",
          "totalCapacity": 1083.0,
          "durationMinute": 26,
          "calorie": 47,
          "actionNum": 16
        },
        {
          "date": "2025-11-02",
          "totalCapacity": 9082.0,
          "durationMinute": 24,
          "calorie": 681,
          "actionNum": 16
        },
        {
          "date": "2025-11-04",
          "totalCapacity": 6689.0,
          "durationMinute": 26,
          "calorie": 370,
          "actionNum": 17
        },
        {
          "date": "2025-11-12",
          "totalCapacity": 10465.0,
          "durationMinute": 26,
          "calorie": 586,
          "actionNum": 17
        },
        {
          "date": "2025-11-16",
          "totalCapacity": 11030.0,
          "durationMinute": 26,
          "calorie": 414,
          "actionNum": 17
        },
        {
          "date": "2025-11-19",
          "totalCapacity": 10734.0,
          "durationMinute": 26,
          "calorie": 400,
          "actionNum": 17
        },
        {
          "date": "2025-11-22",
          "totalCapacity": 7571.0,
          "durationMinute": 26,
          "calorie": 328,
          "actionNum": 17
        },
        {
          "date": "2025-11-25",
          "totalCapacity": 0.0,
          "durationMinute": 26,
          "calorie": 7,
          "actionNum": 17
        },
        {
          "date": "2025-11-25",
          "totalCapacity": 12752.0,
          "durationMinute": 26,
          "calorie": 431,
          "actionNum": 17
        },
        {
          "date": "2025-11-27",
          "totalCapacity": 4868.0,
          "durationMinute": 26,
          "calorie": 288,
          "actionNum": 17
        },
        {
          "date": "2025-11-28",
          "totalCapacity": 4825.0,
          "durationMinute": 26,
          "calorie": 236,
          "actionNum": 17
        },
        {
          "date": "2025-12-11",
          "totalCapacity": 13917.0,
          "durationMinute": 26,
          "calorie": 887,
          "actionNum": 17
        },
        {
          "date": "2026-01-09",
          "totalCapacity": 2293.0,
          "durationMinute": 26,
          "calorie": 161,
          "actionNum": 17
        },
        {
          "date": "2026-01-16",
          "totalCapacity": 12002.0,
          "durationMinute": 26,
          "calorie": 540,
          "actionNum": 17
        },
        {
          "date": "2026-01-22",
          "totalCapacity": 12465.0,
          "durationMinute": 26,
          "calorie": 566,
          "actionNum": 17
        },
        {
          "date": "2026-01-29",
          "totalCapacity": 1666.0,
          "durationMinute": 26,
          "calorie": 161,
          "actionNum": 17
        },
        {
          "date": "2026-01-31",
          "totalCapacity": 5076.0,
          "durationMinute": 26,
          "calorie": 153,
          "actionNum": 17
        },
        {
          "date": "2026-02-06",
          "totalCapacity": 5083.0,
          "durationMinute": 26,
          "calorie": 166,
          "actionNum": 17
        },
        {
          "date": "2026-02-08",
          "totalCapacity": 5052.0,
          "durationMinute": 26,
          "calorie": 210,
          "actionNum": 17
        },
        {
          "date": "2026-02-18",
          "totalCapacity": 11447.0,
          "durationMinute": 26,
          "calorie": 859,
          "actionNum": 17
        },
        {
          "date": "2026-03-17",
          "totalCapacity": 4550.0,
          "durationMinute": 26,
          "calorie": 334,
          "actionNum": 17
        },
        {
          "date": "2026-03-19",
          "totalCapacity": 21.0,
          "durationMinute": 26,
          "calorie": 7,
          "actionNum": 17
        },
        {
          "date": "2026-03-19",
          "totalCapacity": 4563.0,
          "durationMinute": 26,
          "calorie": 319,
          "actionNum": 17
        },
        {
          "date": "2026-03-28",
          "totalCapacity": 0.0,
          "durationMinute": 26,
          "calorie": 34,
          "actionNum": 17
        },
        {
          "date": "2026-03-28",
          "totalCapacity": 722.0,
          "durationMinute": 26,
          "calorie": 77,
          "actionNum": 17
        },
        {
          "date": "2026-03-29",
          "totalCapacity": 7830.0,
          "durationMinute": 26,
          "calorie": 278,
          "actionNum": 17
        },
        {
          "date": "2026-04-07",
          "totalCapacity": 11741.0,
          "durationMinute": 26,
          "calorie": 506,
          "actionNum": 17
        }
      ],
      "exercises": [],
      "muscles": [],
      "bestSession": {
        "date": "2025-12-11",
        "totalCapacity": 13917.0,
        "durationMinute": 26,
        "calorie": 887,
        "actionNum": 17
      },
      "totalSessions": 27,
      "avgVolume": 6575.1,
      "totalVolume": 177527.0
    },
    "Chest handles": {
      "name": "Chest handles",
      "code": "",
      "sessions": [
        {
          "date": "2025-11-03",
          "totalCapacity": 14359.5,
          "durationMinute": 27,
          "calorie": 398,
          "actionNum": 18
        },
        {
          "date": "2025-11-09",
          "totalCapacity": 21458.5,
          "durationMinute": 40,
          "calorie": 678,
          "actionNum": 26
        },
        {
          "date": "2025-11-13",
          "totalCapacity": 6798.5,
          "durationMinute": 40,
          "calorie": 302,
          "actionNum": 26
        },
        {
          "date": "2025-11-17",
          "totalCapacity": 9113.0,
          "durationMinute": 40,
          "calorie": 552,
          "actionNum": 26
        },
        {
          "date": "2025-11-21",
          "totalCapacity": 4335.0,
          "durationMinute": 40,
          "calorie": 218,
          "actionNum": 26
        },
        {
          "date": "2025-11-24",
          "totalCapacity": 5683.5,
          "durationMinute": 40,
          "calorie": 223,
          "actionNum": 26
        },
        {
          "date": "2026-01-25",
          "totalCapacity": 14562.0,
          "durationMinute": 40,
          "calorie": 518,
          "actionNum": 26
        },
        {
          "date": "2026-02-03",
          "totalCapacity": 1421.5,
          "durationMinute": 40,
          "calorie": 114,
          "actionNum": 26
        },
        {
          "date": "2026-02-03",
          "totalCapacity": 10191.5,
          "durationMinute": 40,
          "calorie": 406,
          "actionNum": 26
        }
      ],
      "exercises": [],
      "muscles": [],
      "bestSession": {
        "date": "2025-11-09",
        "totalCapacity": 21458.5,
        "durationMinute": 40,
        "calorie": 678,
        "actionNum": 26
      },
      "totalSessions": 9,
      "avgVolume": 9769.2,
      "totalVolume": 87923.0
    },
    "Warrior 3 (bar)": {
      "name": "Warrior 3 (bar)",
      "code": "",
      "sessions": [
        {
          "date": "2025-11-05",
          "totalCapacity": 7018.0,
          "durationMinute": 30,
          "calorie": 330,
          "actionNum": 20
        },
        {
          "date": "2026-01-13",
          "totalCapacity": 12656.0,
          "durationMinute": 30,
          "calorie": 594,
          "actionNum": 20
        }
      ],
      "exercises": [],
      "muscles": [],
      "bestSession": {
        "date": "2026-01-13",
        "totalCapacity": 12656.0,
        "durationMinute": 30,
        "calorie": 594,
        "actionNum": 20
      },
      "totalSessions": 2,
      "avgVolume": 9837.0,
      "totalVolume": 19674.0
    },
    "Warrior 1": {
      "name": "Warrior 1",
      "code": "",
      "sessions": [
        {
          "date": "2025-11-06",
          "totalCapacity": 7490.5,
          "durationMinute": 53,
          "calorie": 427,
          "actionNum": 30
        },
        {
          "date": "2025-11-10",
          "totalCapacity": 11152.0,
          "durationMinute": 53,
          "calorie": 398,
          "actionNum": 30
        },
        {
          "date": "2025-11-14",
          "totalCapacity": 32887.0,
          "durationMinute": 53,
          "calorie": 846,
          "actionNum": 30
        },
        {
          "date": "2025-11-18",
          "totalCapacity": 8620.0,
          "durationMinute": 53,
          "calorie": 332,
          "actionNum": 30
        },
        {
          "date": "2025-12-07",
          "totalCapacity": 14541.5,
          "durationMinute": 53,
          "calorie": 509,
          "actionNum": 30
        },
        {
          "date": "2025-12-09",
          "totalCapacity": 33203.5,
          "durationMinute": 53,
          "calorie": 1097,
          "actionNum": 30
        },
        {
          "date": "2025-12-19",
          "totalCapacity": 33294.0,
          "durationMinute": 53,
          "calorie": 1597,
          "actionNum": 30
        },
        {
          "date": "2026-01-06",
          "totalCapacity": 19499.0,
          "durationMinute": 53,
          "calorie": 1024,
          "actionNum": 30
        },
        {
          "date": "2026-01-23",
          "totalCapacity": 17802.0,
          "durationMinute": 50,
          "calorie": 651,
          "actionNum": 30
        },
        {
          "date": "2026-01-29",
          "totalCapacity": 27095.0,
          "durationMinute": 50,
          "calorie": 1091,
          "actionNum": 30
        },
        {
          "date": "2026-02-02",
          "totalCapacity": 35305.0,
          "durationMinute": 50,
          "calorie": 1507,
          "actionNum": 30
        },
        {
          "date": "2026-02-10",
          "totalCapacity": 6332.5,
          "durationMinute": 50,
          "calorie": 308,
          "actionNum": 30
        },
        {
          "date": "2026-02-22",
          "totalCapacity": 17903.5,
          "durationMinute": 50,
          "calorie": 764,
          "actionNum": 30
        }
      ],
      "exercises": [],
      "muscles": [],
      "bestSession": {
        "date": "2026-02-02",
        "totalCapacity": 35305.0,
        "durationMinute": 50,
        "calorie": 1507,
        "actionNum": 30
      },
      "totalSessions": 13,
      "avgVolume": 20394.3,
      "totalVolume": 265125.5
    },
    "Warrior 4 (rope)": {
      "name": "Warrior 4 (rope)",
      "code": "",
      "sessions": [
        {
          "date": "2025-11-07",
          "totalCapacity": 1765.0,
          "durationMinute": 50,
          "calorie": 231,
          "actionNum": 34
        }
      ],
      "exercises": [],
      "muscles": [],
      "bestSession": {
        "date": "2025-11-07",
        "totalCapacity": 1765.0,
        "durationMinute": 50,
        "calorie": 231,
        "actionNum": 34
      },
      "totalSessions": 1,
      "avgVolume": 1765.0,
      "totalVolume": 1765.0
    },
    "Deadlift": {
      "name": "Deadlift",
      "code": "",
      "sessions": [
        {
          "date": "2025-11-15",
          "totalCapacity": 0.0,
          "durationMinute": 7,
          "calorie": 10,
          "actionNum": 1
        },
        {
          "date": "2025-11-15",
          "totalCapacity": 1040.0,
          "durationMinute": 7,
          "calorie": 56,
          "actionNum": 1
        },
        {
          "date": "2025-11-15",
          "totalCapacity": 2600.0,
          "durationMinute": 5,
          "calorie": 35,
          "actionNum": 1
        },
        {
          "date": "2025-11-20",
          "totalCapacity": 3120.0,
          "durationMinute": 2,
          "calorie": 35,
          "actionNum": 1
        }
      ],
      "exercises": [],
      "muscles": [],
      "bestSession": {
        "date": "2025-11-20",
        "totalCapacity": 3120.0,
        "durationMinute": 2,
        "calorie": 35,
        "actionNum": 1
      },
      "totalSessions": 4,
      "avgVolume": 1690.0,
      "totalVolume": 6760.0
    },
    "Back Barbell": {
      "name": "Back Barbell",
      "code": "",
      "sessions": [
        {
          "date": "2025-11-20",
          "totalCapacity": 13730.0,
          "durationMinute": 35,
          "calorie": 348,
          "actionNum": 22
        },
        {
          "date": "2026-01-18",
          "totalCapacity": 10552.0,
          "durationMinute": 35,
          "calorie": 341,
          "actionNum": 22
        },
        {
          "date": "2026-01-23",
          "totalCapacity": 8091.0,
          "durationMinute": 31,
          "calorie": 249,
          "actionNum": 22
        },
        {
          "date": "2026-02-03",
          "totalCapacity": 88.0,
          "durationMinute": 31,
          "calorie": 13,
          "actionNum": 22
        },
        {
          "date": "2026-03-12",
          "totalCapacity": 11897.0,
          "durationMinute": 31,
          "calorie": 391,
          "actionNum": 22
        },
        {
          "date": "2026-03-26",
          "totalCapacity": 17.0,
          "durationMinute": 31,
          "calorie": 5,
          "actionNum": 22
        },
        {
          "date": "2026-03-26",
          "totalCapacity": 11953.0,
          "durationMinute": 31,
          "calorie": 575,
          "actionNum": 22
        }
      ],
      "exercises": [],
      "muscles": [],
      "bestSession": {
        "date": "2025-11-20",
        "totalCapacity": 13730.0,
        "durationMinute": 35,
        "calorie": 348,
        "actionNum": 22
      },
      "totalSessions": 7,
      "avgVolume": 8046.9,
      "totalVolume": 56328.0
    },
    "Leg Day": {
      "name": "Leg Day",
      "code": "",
      "sessions": [
        {
          "date": "2025-12-10",
          "totalCapacity": 11804.0,
          "durationMinute": 16,
          "calorie": 489,
          "actionNum": 9
        }
      ],
      "exercises": [],
      "muscles": [],
      "bestSession": {
        "date": "2025-12-10",
        "totalCapacity": 11804.0,
        "durationMinute": 16,
        "calorie": 489,
        "actionNum": 9
      },
      "totalSessions": 1,
      "avgVolume": 11804.0,
      "totalVolume": 11804.0
    },
    "Custom": {
      "name": "Custom",
      "code": "",
      "sessions": [
        {
          "date": "2026-01-24",
          "totalCapacity": 2825.8,
          "durationMinute": 0,
          "calorie": 103,
          "actionNum": 0
        },
        {
          "date": "2026-01-26",
          "totalCapacity": 73.12,
          "durationMinute": 0,
          "calorie": 1,
          "actionNum": 0
        },
        {
          "date": "2026-01-30",
          "totalCapacity": 32.0,
          "durationMinute": 0,
          "calorie": 1,
          "actionNum": 0
        },
        {
          "date": "2026-02-03",
          "totalCapacity": 8.0,
          "durationMinute": 0,
          "calorie": 0,
          "actionNum": 0
        },
        {
          "date": "2026-02-05",
          "totalCapacity": 344.4,
          "durationMinute": 0,
          "calorie": 18,
          "actionNum": 0
        },
        {
          "date": "2026-03-19",
          "totalCapacity": 222.05,
          "durationMinute": 0,
          "calorie": 7,
          "actionNum": 0
        },
        {
          "date": "2026-03-19",
          "totalCapacity": 615.0,
          "durationMinute": 0,
          "calorie": 11,
          "actionNum": 0
        }
      ],
      "exercises": [],
      "muscles": [],
      "bestSession": {
        "date": "2026-01-24",
        "totalCapacity": 2825.8,
        "durationMinute": 0,
        "calorie": 103,
        "actionNum": 0
      },
      "totalSessions": 7,
      "avgVolume": 588.6,
      "totalVolume": 4120.4
    },
    "one arm": {
      "name": "one arm",
      "code": "",
      "sessions": [
        {
          "date": "2026-02-03",
          "totalCapacity": 0.0,
          "durationMinute": 109,
          "calorie": 44,
          "actionNum": 40
        }
      ],
      "exercises": [],
      "muscles": [],
      "bestSession": {
        "date": "2026-02-03",
        "totalCapacity": 0.0,
        "durationMinute": 109,
        "calorie": 44,
        "actionNum": 40
      },
      "totalSessions": 1,
      "avgVolume": 0.0,
      "totalVolume": 0.0
    }
  },
  "exercisePRs": {
    "Standing Barbell Triceps Push Down": {
      "best1RM": 170,
      "workout": "Arms Barbell"
    },
    "Incline Barbell High Cable Biceps Curl": {
      "best1RM": 74,
      "workout": "Arms Barbell"
    },
    "\u200bSupine Barbell High Cable Biceps Curl": {
      "best1RM": 90,
      "workout": "Arms Barbell"
    },
    "Supine Barbell Biceps Curl": {
      "best1RM": 90,
      "workout": "Arms Barbell"
    },
    "\u200bSupine Barbell Overhand Biceps Curl": {
      "best1RM": 72,
      "workout": "Arms Barbell"
    },
    "Standing Barbell Overhead Triceps Extension": {
      "best1RM": 94,
      "workout": "Arms Barbell"
    },
    "Standing Barbell Reverse-Grip Overhead Tricep Extension": {
      "best1RM": 60,
      "workout": "Arms Barbell"
    },
    "Table Top Barbell Triceps Extension": {
      "best1RM": 78,
      "workout": "Arms Barbell"
    },
    "Kneeling Dual-Handle Lat Pulldown": {
      "best1RM": 125,
      "workout": "Warrior 2"
    },
    "Kneeling Dual-Handle High to Low Chest Fly": {
      "best1RM": 50,
      "workout": "Warrior 2"
    },
    "Kneeling Dual-Handle Underhand Lat Pulldown": {
      "best1RM": 80,
      "workout": "Warrior 2"
    },
    "HandsWU-1": {
      "best1RM": 80.0,
      "workout": "Warrior 2"
    },
    "Standing Alternating Chest Press": {
      "best1RM": 53,
      "workout": "Warrior 2"
    },
    "Dual Handle Alternating Bench Press": {
      "best1RM": 92,
      "workout": "Warrior 2"
    },
    "Supine Dual-Handle Chest Fly": {
      "best1RM": 46,
      "workout": "Warrior 2"
    },
    "Seated Dual-Handle Front Raise": {
      "best1RM": 36,
      "workout": "Warrior 2"
    },
    "Seated Dual-Handle Lateral Raise": {
      "best1RM": 36,
      "workout": "Warrior 2"
    },
    "Seated Dual-Handle Shoulder Press": {
      "best1RM": 44,
      "workout": "Warrior 2"
    },
    "Dual-Handle Calf Raise": {
      "best1RM": 93,
      "workout": "Warrior 2"
    },
    "Half-Kneeling Face Pull": {
      "best1RM": 103,
      "workout": "Warrior 4 (rope)"
    },
    "Kneeling Tricep Rope Lat Pulldown": {
      "best1RM": 76,
      "workout": "Warrior 4 (rope)"
    },
    "Incline Tricep Rope Straight Arm Pushdown ": {
      "best1RM": 82,
      "workout": "Warrior 4 (rope)"
    },
    "Seated Tricep Rope Crunch": {
      "best1RM": 46,
      "workout": "Warrior 4 (rope)"
    },
    "Standing High Cable Biceps Curl with Rope Attachment": {
      "best1RM": 70,
      "workout": "Warrior 4 (rope)"
    },
    "Standing High Cable Tricep Rope Curl": {
      "best1RM": 63,
      "workout": "Warrior 4 (rope)"
    },
    "Standing Tricep Rope Face Pull (Rear Delts)": {
      "best1RM": 63,
      "workout": "Warrior 4 (rope)"
    },
    "Standing Tricep Rope Row": {
      "best1RM": 62,
      "workout": "Warrior 4 (rope)"
    },
    "Standing Tricep Rope Overhead Triceps Extension (Main Frame)": {
      "best1RM": 80,
      "workout": "Warrior 4 (rope)"
    },
    "Standing Tricep Rope Shrug": {
      "best1RM": 80,
      "workout": "Warrior 4 (rope)"
    },
    "Standing Tricep Rope Upright Row": {
      "best1RM": 50,
      "workout": "Warrior 4 (rope)"
    },
    "Tricep Rope Romanian Deadlift": {
      "best1RM": 120,
      "workout": "Warrior 4 (rope)"
    },
    "Y-Front Raise": {
      "best1RM": 44,
      "workout": "Warrior 4 (rope)"
    },
    "Standing Tricep Rope Hammer Curl": {
      "best1RM": 70,
      "workout": "Warrior 4 (rope)"
    },
    "Tricep Rope Bent-Over Row": {
      "best1RM": 92,
      "workout": "Warrior 4 (rope)"
    },
    "Seated Tricep Rope Overhead Extension": {
      "best1RM": 38,
      "workout": "Warrior 4 (rope)"
    },
    "Standing Dual-Handle High-to-Low Chest Press": {
      "best1RM": 46,
      "workout": "pulldown"
    },
    "Barbell Deadlift": {
      "best1RM": 388,
      "workout": "Leg Day"
    },
    "Barbell Stiff-Leg Deadlift": {
      "best1RM": 140,
      "workout": "Leg Day"
    },
    "Barbell Hip Thrust": {
      "best1RM": 240,
      "workout": "Leg Day"
    },
    "Kneeling Barbell Lat Pulldown": {
      "best1RM": 294,
      "workout": "Back Barbell"
    },
    "Kneeling Barbell Reverse-Grip Lat Pulldown": {
      "best1RM": 280,
      "workout": "Back Barbell"
    },
    "Seated Barbell Lat Pulldown": {
      "best1RM": 192,
      "workout": "Back Barbell"
    },
    "Seated Barbell Reverse-Grip Lat Pulldown": {
      "best1RM": 248,
      "workout": "Back Barbell"
    },
    "Seated Barbell Wide Reverse-Grip Lat Pulldown": {
      "best1RM": 106,
      "workout": "Back Barbell"
    },
    "Incline Barbell Straight Arm Pushdown": {
      "best1RM": 168,
      "workout": "Back Barbell"
    },
    "Seated Barbell Row": {
      "best1RM": 192,
      "workout": "Back Barbell"
    },
    "Seated Barbell Reverse-Grip Row": {
      "best1RM": 170,
      "workout": "Back Barbell"
    },
    "Seated Barbell Wide Row": {
      "best1RM": 202,
      "workout": "Back Barbell"
    },
    "Barbell Bent Over Row": {
      "best1RM": 198,
      "workout": "Back Barbell"
    },
    "Bent-Over Reverse-Grip Barbell Row": {
      "best1RM": 126,
      "workout": "Back Barbell"
    },
    "Standing Dual-Handle Biceps Curl": {
      "best1RM": 45,
      "workout": "Warrior (Biceps)"
    },
    "Standing Dual-Handle Neutral-Grip Front Raise": {
      "best1RM": 42,
      "workout": "Warrior (Biceps)"
    },
    "Standing Dual-Handle Lateral Raise": {
      "best1RM": 39,
      "workout": "Warrior (Biceps)"
    },
    "Seated Double-Handle Biceps Curl": {
      "best1RM": 67,
      "workout": "Warrior (Biceps)"
    },
    "Incline Dual-Handle Chest Fly (Floor)": {
      "best1RM": 49,
      "workout": "Warrior (Biceps)"
    },
    "Bent-Over Dual-Handle Reverse Fly": {
      "best1RM": 25,
      "workout": "Warrior (Biceps)"
    },
    "Kneeling Dual-Handle High-to-Low Chest Press": {
      "best1RM": 64,
      "workout": "Chest handles"
    },
    "Standing Dual-Handle High-to-Low Chest Fly": {
      "best1RM": 53,
      "workout": "Chest handles"
    },
    "Seated Dual-Handle High-to-Low Chest Fly": {
      "best1RM": 52,
      "workout": "Chest handles"
    },
    "Incline Dual-Handle High-to-Low Chest Fly": {
      "best1RM": 55,
      "workout": "Chest handles"
    },
    "Standing Dual-Handle Low-to-High Chest Press": {
      "best1RM": 54,
      "workout": "Chest handles"
    },
    "Supine Dual-Handle Twist Fly": {
      "best1RM": 54,
      "workout": "Chest handles"
    },
    "Dual-Handle Reverse Grip Bench Press": {
      "best1RM": 52,
      "workout": "Chest handles"
    },
    "Supine Narrow-Grip Dual-Handle Chest Press": {
      "best1RM": 53,
      "workout": "Chest handles"
    },
    "Standing Dual-Handle High Cable Curl": {
      "best1RM": 43,
      "workout": "Warrior 1"
    },
    "Supine Dual-Handle Reverse Fly": {
      "best1RM": 61,
      "workout": "Warrior 1"
    },
    "Seated Dual-Handle Wide Row": {
      "best1RM": 110,
      "workout": "Warrior 1"
    },
    "Dual-Handle Bench Press": {
      "best1RM": 90,
      "workout": "Warrior 1"
    },
    "Seated Dual-Handle Arnold Press": {
      "best1RM": 56,
      "workout": "Warrior 1"
    },
    "Standing Dual-Handle Low-to-High Chest Fly": {
      "best1RM": 48,
      "workout": "Warrior 1"
    },
    "Incline Barbell Close-Grip Chest Press": {
      "best1RM": 125,
      "workout": "Warrior 3 (bar)"
    },
    "Incline Barbell Bench Press": {
      "best1RM": 185,
      "workout": "Warrior 3 (bar)"
    },
    "Barbell Reverse Grip Bench Press": {
      "best1RM": 101,
      "workout": "Warrior 3 (bar)"
    },
    "Barbell Bench Press": {
      "best1RM": 232,
      "workout": "Warrior 3 (bar)"
    },
    "Seated Barbell Z Press": {
      "best1RM": 70,
      "workout": "Warrior 3 (bar)"
    },
    "Bent-Over Barbell Wide Row": {
      "best1RM": 91,
      "workout": "Warrior 3 (bar)"
    },
    "Standing Barbell Calf Raise": {
      "best1RM": 54,
      "workout": "Warrior 3 (bar)"
    },
    "Standing Barbell Front Raise": {
      "best1RM": 54,
      "workout": "Warrior 3 (bar)"
    }
  },
  "totalWorkouts": 79,
  "totalVolumeLbs": 801303.4,
  "dateRange": {
    "start": "2025-11-01",
    "end": "2026-04-07"
  },
  "allSessions": [
    {
      "date": "2025-11-01",
      "title": "Warrior 2",
      "totalCapacity": 14383.5,
      "durationMinute": 65,
      "calorie": 352,
      "actionNum": 34
    },
    {
      "date": "2025-11-01",
      "title": "Arms Barbell",
      "totalCapacity": 1083.0,
      "durationMinute": 26,
      "calorie": 47,
      "actionNum": 16
    },
    {
      "date": "2025-11-02",
      "title": "Arms Barbell",
      "totalCapacity": 9082.0,
      "durationMinute": 24,
      "calorie": 681,
      "actionNum": 16
    },
    {
      "date": "2025-11-03",
      "title": "Chest handles",
      "totalCapacity": 14359.5,
      "durationMinute": 27,
      "calorie": 398,
      "actionNum": 18
    },
    {
      "date": "2025-11-04",
      "title": "Arms Barbell",
      "totalCapacity": 6689.0,
      "durationMinute": 26,
      "calorie": 370,
      "actionNum": 17
    },
    {
      "date": "2025-11-05",
      "title": "Warrior 3 (bar)",
      "totalCapacity": 7018.0,
      "durationMinute": 30,
      "calorie": 330,
      "actionNum": 20
    },
    {
      "date": "2025-11-06",
      "title": "Warrior 1",
      "totalCapacity": 7490.5,
      "durationMinute": 53,
      "calorie": 427,
      "actionNum": 30
    },
    {
      "date": "2025-11-07",
      "title": "Warrior 4 (rope)",
      "totalCapacity": 1765.0,
      "durationMinute": 50,
      "calorie": 231,
      "actionNum": 34
    },
    {
      "date": "2025-11-09",
      "title": "Chest handles",
      "totalCapacity": 21458.5,
      "durationMinute": 40,
      "calorie": 678,
      "actionNum": 26
    },
    {
      "date": "2025-11-10",
      "title": "Warrior 1",
      "totalCapacity": 11152.0,
      "durationMinute": 53,
      "calorie": 398,
      "actionNum": 30
    },
    {
      "date": "2025-11-12",
      "title": "Arms Barbell",
      "totalCapacity": 10465.0,
      "durationMinute": 26,
      "calorie": 586,
      "actionNum": 17
    },
    {
      "date": "2025-11-13",
      "title": "Chest handles",
      "totalCapacity": 6798.5,
      "durationMinute": 40,
      "calorie": 302,
      "actionNum": 26
    },
    {
      "date": "2025-11-14",
      "title": "Warrior 1",
      "totalCapacity": 32887.0,
      "durationMinute": 53,
      "calorie": 846,
      "actionNum": 30
    },
    {
      "date": "2025-11-15",
      "title": "Deadlift",
      "totalCapacity": 0.0,
      "durationMinute": 7,
      "calorie": 10,
      "actionNum": 1
    },
    {
      "date": "2025-11-15",
      "title": "Deadlift",
      "totalCapacity": 1040.0,
      "durationMinute": 7,
      "calorie": 56,
      "actionNum": 1
    },
    {
      "date": "2025-11-15",
      "title": "Deadlift",
      "totalCapacity": 2600.0,
      "durationMinute": 5,
      "calorie": 35,
      "actionNum": 1
    },
    {
      "date": "2025-11-16",
      "title": "Arms Barbell",
      "totalCapacity": 11030.0,
      "durationMinute": 26,
      "calorie": 414,
      "actionNum": 17
    },
    {
      "date": "2025-11-17",
      "title": "Chest handles",
      "totalCapacity": 9113.0,
      "durationMinute": 40,
      "calorie": 552,
      "actionNum": 26
    },
    {
      "date": "2025-11-18",
      "title": "Warrior 1",
      "totalCapacity": 8620.0,
      "durationMinute": 53,
      "calorie": 332,
      "actionNum": 30
    },
    {
      "date": "2025-11-19",
      "title": "Arms Barbell",
      "totalCapacity": 10734.0,
      "durationMinute": 26,
      "calorie": 400,
      "actionNum": 17
    },
    {
      "date": "2025-11-20",
      "title": "Deadlift",
      "totalCapacity": 3120.0,
      "durationMinute": 2,
      "calorie": 35,
      "actionNum": 1
    },
    {
      "date": "2025-11-20",
      "title": "Back Barbell",
      "totalCapacity": 13730.0,
      "durationMinute": 35,
      "calorie": 348,
      "actionNum": 22
    },
    {
      "date": "2025-11-21",
      "title": "Chest handles",
      "totalCapacity": 4335.0,
      "durationMinute": 40,
      "calorie": 218,
      "actionNum": 26
    },
    {
      "date": "2025-11-22",
      "title": "Arms Barbell",
      "totalCapacity": 7571.0,
      "durationMinute": 26,
      "calorie": 328,
      "actionNum": 17
    },
    {
      "date": "2025-11-24",
      "title": "Chest handles",
      "totalCapacity": 5683.5,
      "durationMinute": 40,
      "calorie": 223,
      "actionNum": 26
    },
    {
      "date": "2025-11-25",
      "title": "Arms Barbell",
      "totalCapacity": 0.0,
      "durationMinute": 26,
      "calorie": 7,
      "actionNum": 17
    },
    {
      "date": "2025-11-25",
      "title": "Arms Barbell",
      "totalCapacity": 12752.0,
      "durationMinute": 26,
      "calorie": 431,
      "actionNum": 17
    },
    {
      "date": "2025-11-27",
      "title": "Arms Barbell",
      "totalCapacity": 4868.0,
      "durationMinute": 26,
      "calorie": 288,
      "actionNum": 17
    },
    {
      "date": "2025-11-28",
      "title": "Arms Barbell",
      "totalCapacity": 4825.0,
      "durationMinute": 26,
      "calorie": 236,
      "actionNum": 17
    },
    {
      "date": "2025-12-07",
      "title": "Warrior 1",
      "totalCapacity": 14541.5,
      "durationMinute": 53,
      "calorie": 509,
      "actionNum": 30
    },
    {
      "date": "2025-12-09",
      "title": "Warrior 1",
      "totalCapacity": 33203.5,
      "durationMinute": 53,
      "calorie": 1097,
      "actionNum": 30
    },
    {
      "date": "2025-12-10",
      "title": "Leg Day",
      "totalCapacity": 11804.0,
      "durationMinute": 16,
      "calorie": 489,
      "actionNum": 9
    },
    {
      "date": "2025-12-11",
      "title": "Arms Barbell",
      "totalCapacity": 13917.0,
      "durationMinute": 26,
      "calorie": 887,
      "actionNum": 17
    },
    {
      "date": "2025-12-12",
      "title": "Warrior 2",
      "totalCapacity": 9018.0,
      "durationMinute": 65,
      "calorie": 436,
      "actionNum": 34
    },
    {
      "date": "2025-12-15",
      "title": "Warrior 2",
      "totalCapacity": 41058.0,
      "durationMinute": 65,
      "calorie": 1511,
      "actionNum": 34
    },
    {
      "date": "2025-12-19",
      "title": "Warrior 1",
      "totalCapacity": 33294.0,
      "durationMinute": 53,
      "calorie": 1597,
      "actionNum": 30
    },
    {
      "date": "2026-01-06",
      "title": "Warrior 1",
      "totalCapacity": 19499.0,
      "durationMinute": 53,
      "calorie": 1024,
      "actionNum": 30
    },
    {
      "date": "2026-01-07",
      "title": "Warrior 2",
      "totalCapacity": 20698.0,
      "durationMinute": 66,
      "calorie": 1011,
      "actionNum": 34
    },
    {
      "date": "2026-01-09",
      "title": "Arms Barbell",
      "totalCapacity": 2293.0,
      "durationMinute": 26,
      "calorie": 161,
      "actionNum": 17
    },
    {
      "date": "2026-01-11",
      "title": "Warrior 2",
      "totalCapacity": 41481.5,
      "durationMinute": 66,
      "calorie": 1371,
      "actionNum": 34
    },
    {
      "date": "2026-01-13",
      "title": "Warrior 3 (bar)",
      "totalCapacity": 12656.0,
      "durationMinute": 30,
      "calorie": 594,
      "actionNum": 20
    },
    {
      "date": "2026-01-16",
      "title": "Arms Barbell",
      "totalCapacity": 12002.0,
      "durationMinute": 26,
      "calorie": 540,
      "actionNum": 17
    },
    {
      "date": "2026-01-18",
      "title": "Back Barbell",
      "totalCapacity": 10552.0,
      "durationMinute": 35,
      "calorie": 341,
      "actionNum": 22
    },
    {
      "date": "2026-01-22",
      "title": "Arms Barbell",
      "totalCapacity": 12465.0,
      "durationMinute": 26,
      "calorie": 566,
      "actionNum": 17
    },
    {
      "date": "2026-01-23",
      "title": "Warrior 1",
      "totalCapacity": 17802.0,
      "durationMinute": 50,
      "calorie": 651,
      "actionNum": 30
    },
    {
      "date": "2026-01-23",
      "title": "Back Barbell",
      "totalCapacity": 8091.0,
      "durationMinute": 31,
      "calorie": 249,
      "actionNum": 22
    },
    {
      "date": "2026-01-24",
      "title": "Custom",
      "totalCapacity": 2825.8,
      "durationMinute": 0,
      "calorie": 103,
      "actionNum": 0
    },
    {
      "date": "2026-01-25",
      "title": "Chest handles",
      "totalCapacity": 14562.0,
      "durationMinute": 40,
      "calorie": 518,
      "actionNum": 26
    },
    {
      "date": "2026-01-26",
      "title": "Custom",
      "totalCapacity": 73.12,
      "durationMinute": 0,
      "calorie": 1,
      "actionNum": 0
    },
    {
      "date": "2026-01-27",
      "title": "Warrior 2",
      "totalCapacity": 22014.5,
      "durationMinute": 64,
      "calorie": 939,
      "actionNum": 34
    },
    {
      "date": "2026-01-29",
      "title": "Warrior 1",
      "totalCapacity": 27095.0,
      "durationMinute": 50,
      "calorie": 1091,
      "actionNum": 30
    },
    {
      "date": "2026-01-29",
      "title": "Arms Barbell",
      "totalCapacity": 1666.0,
      "durationMinute": 26,
      "calorie": 161,
      "actionNum": 17
    },
    {
      "date": "2026-01-30",
      "title": "Custom",
      "totalCapacity": 32.0,
      "durationMinute": 0,
      "calorie": 1,
      "actionNum": 0
    },
    {
      "date": "2026-01-31",
      "title": "Arms Barbell",
      "totalCapacity": 5076.0,
      "durationMinute": 26,
      "calorie": 153,
      "actionNum": 17
    },
    {
      "date": "2026-02-02",
      "title": "Warrior 1",
      "totalCapacity": 35305.0,
      "durationMinute": 50,
      "calorie": 1507,
      "actionNum": 30
    },
    {
      "date": "2026-02-03",
      "title": "Custom",
      "totalCapacity": 8.0,
      "durationMinute": 0,
      "calorie": 0,
      "actionNum": 0
    },
    {
      "date": "2026-02-03",
      "title": "Back Barbell",
      "totalCapacity": 88.0,
      "durationMinute": 31,
      "calorie": 13,
      "actionNum": 22
    },
    {
      "date": "2026-02-03",
      "title": "Chest handles",
      "totalCapacity": 1421.5,
      "durationMinute": 40,
      "calorie": 114,
      "actionNum": 26
    },
    {
      "date": "2026-02-03",
      "title": "one arm",
      "totalCapacity": 0.0,
      "durationMinute": 109,
      "calorie": 44,
      "actionNum": 40
    },
    {
      "date": "2026-02-03",
      "title": "Chest handles",
      "totalCapacity": 10191.5,
      "durationMinute": 40,
      "calorie": 406,
      "actionNum": 26
    },
    {
      "date": "2026-02-05",
      "title": "Custom",
      "totalCapacity": 344.4,
      "durationMinute": 0,
      "calorie": 18,
      "actionNum": 0
    },
    {
      "date": "2026-02-06",
      "title": "Arms Barbell",
      "totalCapacity": 5083.0,
      "durationMinute": 26,
      "calorie": 166,
      "actionNum": 17
    },
    {
      "date": "2026-02-08",
      "title": "Arms Barbell",
      "totalCapacity": 5052.0,
      "durationMinute": 26,
      "calorie": 210,
      "actionNum": 17
    },
    {
      "date": "2026-02-10",
      "title": "Warrior 1",
      "totalCapacity": 6332.5,
      "durationMinute": 50,
      "calorie": 308,
      "actionNum": 30
    },
    {
      "date": "2026-02-12",
      "title": "Warrior 2",
      "totalCapacity": 21623.0,
      "durationMinute": 64,
      "calorie": 889,
      "actionNum": 34
    },
    {
      "date": "2026-02-18",
      "title": "Arms Barbell",
      "totalCapacity": 11447.0,
      "durationMinute": 26,
      "calorie": 859,
      "actionNum": 17
    },
    {
      "date": "2026-02-22",
      "title": "Warrior 1",
      "totalCapacity": 17903.5,
      "durationMinute": 50,
      "calorie": 764,
      "actionNum": 30
    },
    {
      "date": "2026-03-12",
      "title": "Back Barbell",
      "totalCapacity": 11897.0,
      "durationMinute": 31,
      "calorie": 391,
      "actionNum": 22
    },
    {
      "date": "2026-03-17",
      "title": "Arms Barbell",
      "totalCapacity": 4550.0,
      "durationMinute": 26,
      "calorie": 334,
      "actionNum": 17
    },
    {
      "date": "2026-03-19",
      "title": "Custom",
      "totalCapacity": 222.05,
      "durationMinute": 0,
      "calorie": 7,
      "actionNum": 0
    },
    {
      "date": "2026-03-19",
      "title": "Custom",
      "totalCapacity": 615.0,
      "durationMinute": 0,
      "calorie": 11,
      "actionNum": 0
    },
    {
      "date": "2026-03-19",
      "title": "Arms Barbell",
      "totalCapacity": 21.0,
      "durationMinute": 26,
      "calorie": 7,
      "actionNum": 17
    },
    {
      "date": "2026-03-19",
      "title": "Arms Barbell",
      "totalCapacity": 4563.0,
      "durationMinute": 26,
      "calorie": 319,
      "actionNum": 17
    },
    {
      "date": "2026-03-26",
      "title": "Back Barbell",
      "totalCapacity": 17.0,
      "durationMinute": 31,
      "calorie": 5,
      "actionNum": 22
    },
    {
      "date": "2026-03-26",
      "title": "Back Barbell",
      "totalCapacity": 11953.0,
      "durationMinute": 31,
      "calorie": 575,
      "actionNum": 22
    },
    {
      "date": "2026-03-28",
      "title": "Arms Barbell",
      "totalCapacity": 0.0,
      "durationMinute": 26,
      "calorie": 34,
      "actionNum": 17
    },
    {
      "date": "2026-03-28",
      "title": "Arms Barbell",
      "totalCapacity": 722.0,
      "durationMinute": 26,
      "calorie": 77,
      "actionNum": 17
    },
    {
      "date": "2026-03-29",
      "title": "Arms Barbell",
      "totalCapacity": 7830.0,
      "durationMinute": 26,
      "calorie": 278,
      "actionNum": 17
    },
    {
      "date": "2026-04-07",
      "title": "Arms Barbell",
      "totalCapacity": 11741.0,
      "durationMinute": 26,
      "calorie": 506,
      "actionNum": 17
    }
  ]
}